undo_stack/__init__.py
undo_stack/_get_version.py
undo_stack/signal.py
undo_stack/signal_container.py
undo_stack/signal_container_spy.py
undo_stack/undo_command.py
undo_stack/undo_group.py
undo_stack/undo_stack.py
py_undo_stack-1.1.0.dist-info/METADATA
py_undo_stack-1.1.0.dist-info/WHEEL
py_undo_stack-1.1.0.dist-info/licenses/LICENSE
py_undo_stack-1.1.0.dist-info/RECORD
