Metadata-Version: 2.4
Name: py-undo-stack
Version: 1.1.0
Summary: Pure python Undo / Redo command stack
Author-email: Thibault Pelletier <thibault.pelletier@kitware.com>
License: BSD 3-Clause License
License-File: LICENSE
Keywords: action tracking,developer tools,history,redo,reversible actions,stack,state management,time travel,undo,utilities
Classifier: Development Status :: 5 - Production/Stable
Classifier: Intended Audience :: Developers
Classifier: License :: OSI Approved :: BSD License
Classifier: Programming Language :: Python
Classifier: Programming Language :: Python :: 3
Classifier: Programming Language :: Python :: 3.9
Classifier: Programming Language :: Python :: 3.10
Classifier: Programming Language :: Python :: 3.11
Classifier: Programming Language :: Python :: 3.12
Classifier: Programming Language :: Python :: 3.13
Classifier: Topic :: Software Development :: Libraries
Classifier: Topic :: Software Development :: Libraries :: Python Modules
Classifier: Topic :: Utilities
Requires-Python: >=3.9
Provides-Extra: dev
Requires-Dist: nox; extra == 'dev'
Requires-Dist: pre-commit; extra == 'dev'
Requires-Dist: pytest-asyncio; extra == 'dev'
Requires-Dist: pytest-cov>=3; extra == 'dev'
Requires-Dist: pytest>=6; extra == 'dev'
Requires-Dist: ruff; extra == 'dev'
